responsive/context_processors.py
responsive/middleware.py
responsive/__init__.py
responsive/views.py
responsive/models.py
responsive/conf.py
responsive/tests/__init__.py
responsive/tests/test_context_processors.py
responsive/tests/test_middleware.py
responsive/static/responsive/js/responsive.js
responsive/static/responsive/js/responsive.min.js
django_responsive-0.3.0.dist-info/RECORD
django_responsive-0.3.0.dist-info/WHEEL
django_responsive-0.3.0.dist-info/METADATA
django_responsive-0.3.0.dist-info/DESCRIPTION.rst
django_responsive-0.3.0.dist-info/top_level.txt
django_responsive-0.3.0.dist-info/metadata.json
